README.txt
setup.py
Chandler_debugPlugin.egg-info/PKG-INFO
Chandler_debugPlugin.egg-info/SOURCES.txt
Chandler_debugPlugin.egg-info/dependency_links.txt
Chandler_debugPlugin.egg-info/entry_points.txt
Chandler_debugPlugin.egg-info/resources_test.ini
Chandler_debugPlugin.egg-info/top_level.txt
Chandler_debugPlugin.egg-info/zip-safe
Chandler_debugPlugin.egg-info/locale/es/es.mo
Chandler_debugPlugin.egg-info/locale/es/es.po
Chandler_debugPlugin.egg-info/locale/es/html/test2.html
Chandler_debugPlugin.egg-info/locale/es/html/test3.html
Chandler_debugPlugin.egg-info/locale/fr/fr.mo
Chandler_debugPlugin.egg-info/locale/fr/fr.po
Chandler_debugPlugin.egg-info/locale/fr/html/test.html
Chandler_debugPlugin.egg-info/locale/fr/html/test2.html
Chandler_debugPlugin.egg-info/locale/fr/images/test.png
Chandler_debugPlugin.egg-info/locale/fr/images/test2.png
Chandler_debugPlugin.egg-info/resources/test.txt
Chandler_debugPlugin.egg-info/resources/html/test.html
Chandler_debugPlugin.egg-info/resources/html/test1.html
Chandler_debugPlugin.egg-info/resources/images/test.png
Chandler_debugPlugin.egg-info/resources/images/test1.png
debug/DebugMenu.py
debug/GenerateItemsFromFile.py
debug/MeMenu.py
debug/SharingMenu.py
debug/TestMenu.py
debug/__init__.py
debug/createItems.py
debug/generate.py
debug/itemGenCollections.txt
debug/itemGenLocations.txt
debug/itemGenNotes.txt
debug/itemGenTitles.txt
debug/mail.py
debug/blockviewer/__init__.py
debug/blockviewer/blockviewer.py
debug/generate_dialog/ItemGenerator.py
debug/generate_dialog/ItemGenerator.xrc
debug/generate_dialog/__init__.py
debug/generate_dialog/itemGenHelp.xcfg
debug/generate_dialog/itemGenHelp.xrc
debug/generate_dialog/itemGenHelp_xrc.py
debug/i18n_tests/test_GB2312
debug/i18n_tests/test_GB2312-2
debug/i18n_tests/test_GB2312_broken
debug/i18n_tests/test_ISO-2022-JP
debug/i18n_tests/test_ISO-2022-JP-2
debug/i18n_tests/test_ISO-2022-JP-3
debug/i18n_tests/test_Windows-1251-2
debug/i18n_tests/test_Windows-1251-3
debug/i18n_tests/test_Windows-1251-4
debug/i18n_tests/test_decode_headers
debug/i18n_tests/test_i18n_utf8
debug/i18n_tests/test_iso-8859-1
debug/i18n_tests/test_iso-8859-13
debug/i18n_tests/test_iso-8859-1_alternative
debug/i18n_tests/test_iso-8859-4
debug/i18n_tests/test_iso-8859-5
debug/i18n_tests/test_junk_russian
debug/i18n_tests/test_no_charset
debug/i18n_tests/test_taiwan
debug/i18n_tests/test_utf-8
debug/i18n_tests/test_utf-8-2
debug/i18n_tests/test_windows-1251
debug/i18n_tests/test_windows-1257
debug/i18n_tests/test_windows_1251
debug/mime_tests/test_alternative
debug/mime_tests/test_digest-containing-boundary
debug/mime_tests/test_digest02
debug/mime_tests/test_digest03
debug/mime_tests/test_digest04
debug/mime_tests/test_fax-bounce
debug/mime_tests/test_forward01
debug/mime_tests/test_lotus_multimixed
debug/mime_tests/test_multi-alt-signed
debug/mime_tests/test_multi-digest-horror
debug/mime_tests/test_multi-text+ext
debug/mime_tests/test_multi-text+ext.2
debug/mime_tests/test_multiple_nested_multiples
debug/mime_tests/test_multiple_same_boundary
